Metadata-Version: 2.1
Name: qiniu-uploader
Version: 0.1.0
Summary: 一个用于将目录上传至七牛云存储的Python包,将服务器数据迁移到七牛云
Home-page: https://github.com/Mr-J-J/qiniu_uploader
Author: Mrj
Author-email: 806189218@qq.com
License: UNKNOWN
Platform: UNKNOWN
Classifier: Programming Language :: Python :: 3
Classifier: License :: OSI Approved :: MIT License
Classifier: Operating System :: OS Independent
Requires-Python: >=2.7,>=3.6
